hack4u_tejadon/__init__.py
hack4u_tejadon/courses.py
hack4u_tejadon/utils.py
hack4u_tejadon-1.0.4.dist-info/METADATA
hack4u_tejadon-1.0.4.dist-info/WHEEL
hack4u_tejadon-1.0.4.dist-info/top_level.txt
hack4u_tejadon-1.0.4.dist-info/RECORD
