Metadata-Version: 2.1
Name: hack4u_tejadon
Version: 1.0.4
Summary: Una biblioteca para consultar curso de hack4u
Home-page: https://hack4u.io
Author: Jesús T.
